Workbook

Sheet Dashboard
A1: TERRY BAKERS — PRODUCTION & MANAGEMENT DASHBOARD
A3: Management overview | Production • Sales • Stock • Costs • Profit
A5: TOTAL SALES | D5: NET PROFIT | G5: CAKES SOLD | J5: CAKES IN STOCK
A6: =Dashboard!E3 -> 0 | D6: =Dashboard!E12 -> 0 | G6: =Dashboard!C4 -> 0 | J6: =Dashboard!C5 -> 0
A9: INGREDIENT BALANCE | D9: INGREDIENT COST | G9: SALES RETURNS | J9: CUSTOMER OUTSTANDING
A10: =Dashboard!A5 -> TOTAL SALES | D10: =Dashboard!E4 -> 0 | G10: =Dashboard!E9 -> 0 | J10: =Dashboard!E11 -> 0
A14: OPERATIONAL SNAPSHOT | H14: MANAGEMENT FOCUS
A15: Total Ingredients Received | D15: =Dashboard!A3 -> Management overview | Production • Sales • Stock • Costs • Profit | H15: • Monitor cakes in stock against daily demand.
A16: Total Ingredients Used | D16: =Dashboard!A4 -> 0 | H16: • Review sales returns and damage values weekly.
A17: Total Cakes Produced | D17: =Dashboard!C3 -> 0 | H17: • Track ingredient usage against production volume.
A18: Total Sales Returns | D18: =Dashboard!E9 -> 0 | H18: • Follow up customer outstanding balances promptly.
A19: Total Damage Value | D19: =Dashboard!E10 -> 0 | H19: • Compare sales and net profit each month.
A20: Average Profit Margin | D20: =Dashboard!E13 -> 0
A22: Metric | B22: Value | D22: Production Metric | E22: Quantity
A23: Sales | B23: =Dashboard!E3 -> 0 | D23: Cakes Produced | E23: =Dashboard!C3 -> 0
A24: Net Profit | B24: =Dashboard!E12 -> 0 | D24: Cakes Sold | E24: =Dashboard!C4 -> 0
A25: Ingredient Cost | B25: =Dashboard!E4 -> 0 | D25: Cakes in Stock | E25: =Dashboard!C5 -> 0
A26: Sales Returns | B26: =Dashboard!E9 -> 0
A27: Damage Value | B27: =Dashboard!E10 -> 0

Sheet Ingredients In(Purchases)
A1: Date | B1: Ingredient | C1: Unit | D1: Quantity In | E1: Cost/Unit | F1: Total Cost | G1: Supplier | H1: Batch/Reference
B2: Flour | C2: kg | D2: 10 | E2: 200 | F2: =IF(OR(D2="",E2=""),"",D2*E2) -> 2000 | H2: B0001
B3: Sobate | C3: kg | D3: 20 | E3: 150 | F3: =IF(OR(D3="",E3=""),"",D3*E3) -> 3000 | H3: B0001
B4: Flavour | C4: Litre | D4: 20 | E4: 150 | F4: =IF(OR(D4="",E4=""),"",D4*E4) -> 3000 | H4: B0001
B5: Eggs | C5: pcs | D5: 30 | E5: 450 | F5: =IF(OR(D5="",E5=""),"",D5*E5) -> 13500 | H5: B0001
B6: Fat | C6: kg | D6: 30 | E6: 200 | F6: =IF(OR(D6="",E6=""),"",D6*E6) -> 6000 | H6: B0001
B7: Sugar | C7: kg | D7: 50 | E7: 150 | F7: =IF(OR(D7="",E7=""),"",D7*E7) -> 7500 | H7: B0001
B8: Glucose | C8: kg | D8: 50 | E8: 100 | F8: =IF(OR(D8="",E8=""),"",D8*E8) -> 5000 | H8: B0001
B9: Packaging | C9: pcs | D9: 60 | E9: 150 | F9: =IF(OR(D9="",E9=""),"",D9*E9) -> 9000 | H9: B0001
B10: Flour | H10: B0002
B11: Sobate | H11: B0002
B12: Flavour | F12: =IF(OR(D12="",E12=""),"",D12*E12) | H12: B0002
B13: Eggs | F13: =IF(OR(D13="",E13=""),"",D13*E13) | H13: B0002
B14: Fat | F14: =IF(OR(D14="",E14=""),"",D14*E14) | H14: B0002
B15: Sugar | F15: =IF(OR(D15="",E15=""),"",D15*E15) | H15: B0002
B16: Glucose | F16: =IF(OR(D16="",E16=""),"",D16*E16) | H16: B0002
B17: Packaging | F17: =IF(OR(D17="",E17=""),"",D17*E17) | H17: B0002
F18: =IF(OR(D18="",E18=""),"",D18*E18)
F19: =IF(OR(D19="",E19=""),"",D19*E19)
F20: =IF(OR(D20="",E20=""),"",D20*E20)
F21: =IF(OR(D21="",E21=""),"",D21*E21)
F22: =IF(OR(D22="",E22=""),"",D22*E22)
F23: =IF(OR(D23="",E23=""),"",D23*E23)
F24: =IF(OR(D24="",E24=""),"",D24*E24)
F25: =IF(OR(D25="",E25=""),"",D25*E25)
F26: =IF(OR(D26="",E26=""),"",D26*E26)
F27: =IF(OR(D27="",E27=""),"",D27*E27)
F28: =IF(OR(D28="",E28=""),"",D28*E28)
F29: =IF(OR(D29="",E29=""),"",D29*E29)
... F101: =IF(OR(D101="",E101=""),"",D101*E101)

Sheet Ingredients Used
A1: Date | B1: Cake Type | C1: Ingredient | D1: Unit | E1: Quantity Used | F1: No. of Cakes | G1: Batch/Reference | H1: Notes
B2: Queen cake | C2: Flour | D2: kg | E2: 5 | F2: 500 | G2: B0001
B3: Queen cake | C3: Sobate | D3: kg | E3: 6 | F3: 500 | G3: B0001
B4: Queen cake | C4: Flavour | D4: Litre | E4: 2 | F4: 500 | G4: B0001
B5: Queen cake | C5: Eggs | D5: pcs | E5: 20 | F5: 500 | G5: B0001
B6: Queen cake | C6: Fat | D6: kg | E6: 10 | F6: 500 | G6: B0001
B7: Queen cake | C7: Sugar | D7: kg | E7: 15 | F7: 500 | G7: B0001
B8: Queen cake | C8: Glucose | D8: kg | E8: 15 | F8: 500 | G8: B0001
B9: Queen cake | C9: Packaging | D9: pcs | E9: 10 | F9: 500 | G9: B0001
B10: Heart cake | C10: Flour | E10: 10 | F10: 600 | G10: B0002
B11: Heart cake | C11: Sobate | E11: 4 | G11: B0002
B12: Heart cake | C12: Flavour | E12: 2 | G12: B0002
B13: Heart cake | C13: Eggs | E13: 15 | G13: B0002
B14: Heart cake | C14: Fat | E14: 15 | G14: B0002
B15: Heart cake | C15: Sugar | E15: 20 | G15: B0002
B16: Heart cake | C16: Glucose | E16: 10 | G16: B0002
B17: Heart cake | C17: Packaging | E17: 10 | G17: B0002

Sheet Production
A1: Date | B1: Product | C1: Batch | D1: Quantity(cake produced) | E1: Worker | F1: Production Hours | G1: Notes
B2: Queen cake | C2: B0001 | D2: 500
B3: Heart cake | C3: B0001 | D3: 400
B4: Round cake | C4: B0001 | D4: 500

Sheet Sales
A1: Date | B1: Product | C1: Customer | D1: Quantity Sold | E1: Selling Price/Cake | F1: Sales Amount | G1: Payment Status | H1: Reference
B2: Queen cake | D2: 300 | E2: 50 | F2: =IF(OR(D2="",E2=""),"",D2*E2) -> 15000 | H2: B0001
B3: Heart cake | D3: 300 | E3: 50 | F3: =IF(OR(D3="",E3=""),"",D3*E3) -> 15000 | H3: B0001
B4: Round cake | D4: 250 | E4: 60 | F4: =IF(OR(D4="",E4=""),"",D4*E4) -> 15000
F5: =IF(OR(D5="",E5=""),"",D5*E5)
F6: =IF(OR(D6="",E6=""),"",D6*E6)
F7: =IF(OR(D7="",E7=""),"",D7*E7)
F8: =IF(OR(D8="",E8=""),"",D8*E8)
F9: =IF(OR(D9="",E9=""),"",D9*E9)
F10: =IF(OR(D10="",E10=""),"",D10*E10)
F11: =IF(OR(D11="",E11=""),"",D11*E11)
F12: =IF(OR(D12="",E12=""),"",D12*E12)
F13: =IF(OR(D13="",E13=""),"",D13*E13)
F14: =IF(OR(D14="",E14=""),"",D14*E14)
F15: =IF(OR(D15="",E15=""),"",D15*E15)
F16: =IF(OR(D16="",E16=""),"",D16*E16)
... F101: =IF(OR(D101="",E101=""),"",D101*E101)

Sheet Cake Balance
A1: Cake Type | B1: Total Produced | C1: Total Sold | D1: Cakes Balance
A2: Queen cake | B2: =IF(A2="","",SUMIF(Production!B:B,A2,Production!D:D)) -> 500 | C2: =IF(A2="","",SUMIF(Sales!B:B,A2,Sales!D:D)) -> 300 | D2: =IF(A2="","",B2-C2) -> 200
A3: Heart cake | B3: =IF(A3="","",SUMIF(Production!B:B,A3,Production!D:D)) -> 400 | C3: =IF(A3="","",SUMIF(Sales!B:B,A3,Sales!D:D)) -> 300 | D3: =IF(A3="","",B3-C3) -> 100
A4: Round cake | B4: =IF(A4="","",SUMIF(Production!B:B,A4,Production!D:D)) -> 500 | C4: =IF(A4="","",SUMIF(Sales!B:B,A4,Sales!D:D)) -> 250 | D4: =IF(A4="","",B4-C4) -> 250
B5: =IF(A5="","",SUMIF(Production!B:B,A5,Production!D:D)) | C5: =IF(A5="","",SUMIF(Sales!B:B,A5,Sales!D:D)) | D5: =IF(A5="","",B5-C5)
B6: =IF(A6="","",SUMIF(Production!B:B,A6,Production!D:D)) | C6: =IF(A6="","",SUMIF(Sales!B:B,A6,Sales!D:D)) | D6: =IF(A6="","",B6-C6)
B7: =IF(A7="","",SUMIF(Production!B:B,A7,Production!D:D)) | C7: =IF(A7="","",SUMIF(Sales!B:B,A7,Sales!D:D)) | D7: =IF(A7="","",B7-C7)
B8: =IF(A8="","",SUMIF(Production!B:B,A8,Production!D:D)) | C8: =IF(A8="","",SUMIF(Sales!B:B,A8,Sales!D:D)) | D8: =IF(A8="","",B8-C8)
B9: =IF(A9="","",SUMIF(Production!B:B,A9,Production!D:D)) | C9: =IF(A9="","",SUMIF(Sales!B:B,A9,Sales!D:D)) | D9: =IF(A9="","",B9-C9)
B10: =IF(A10="","",SUMIF(Production!B:B,A10,Production!D:D)) | C10: =IF(A10="","",SUMIF(Sales!B:B,A10,Sales!D:D)) | D10: =IF(A10="","",B10-C10)
B11: =IF(A11="","",SUMIF(Production!B:B,A11,Production!D:D)) | C11: =IF(A11="","",SUMIF(Sales!B:B,A11,Sales!D:D)) | D11: =IF(A11="","",B11-C11)
B12: =IF(A12="","",SUMIF(Production!B:B,A12,Production!D:D)) | C12: =IF(A12="","",SUMIF(Sales!B:B,A12,Sales!D:D)) | D12: =IF(A12="","",B12-C12)
B13: =IF(A13="","",SUMIF(Production!B:B,A13,Production!D:D)) | C13: =IF(A13="","",SUMIF(Sales!B:B,A13,Sales!D:D)) | D13: =IF(A13="","",B13-C13)
B14: =IF(A14="","",SUMIF(Production!B:B,A14,Production!D:D)) | C14: =IF(A14="","",SUMIF(Sales!B:B,A14,Sales!D:D)) | D14: =IF(A14="","",B14-C14)
B15: =IF(A15="","",SUMIF(Production!B:B,A15,Production!D:D)) | C15: =IF(A15="","",SUMIF(Sales!B:B,A15,Sales!D:D)) | D15: =IF(A15="","",B15-C15)
B16: =IF(A16="","",SUMIF(Production!B:B,A16,Production!D:D)) | C16: =IF(A16="","",SUMIF(Sales!B:B,A16,Sales!D:D)) | D16: =IF(A16="","",B16-C16)
... B51: =IF(A51="","",SUMIF(Production!B:B,A51,Production!D:D)) | C51: =IF(A51="","",SUMIF(Sales!B:B,A51,Sales!D:D)) | D51: =IF(A51="","",B51-C51)

Sheet Ingredients Balances
A1: Ingredient | B1: Unit | C1: Total In | D1: Total Used | E1: Ingredient Balance | F1: Total Cost In | G1: Average Cost/Unit
A2: Flour | B2: kg | C2: =IF(A2="","",SUMIF('Ingredients In(Purchases)'!B:B,A2,'Ingredients In(Purchases)'!D:D)) -> 10 | D2: =IF(A2="","",SUMIF('Ingredients Used'!C:C,A2,'Ingredients Used'!E:E)) -> 15 | E2: =IF(A2="","",C2-D2) -> -5 | F2: =IF(A2="","",SUMIF('Ingredients In(Purchases)'!B:B,A2,'Ingredients In(Purchases)'!F:F)) -> 2000 | G2: =IFERROR(F2/C2,"") -> 200
A3: Sobate | B3: kg | C3: =IF(A3="","",SUMIF('Ingredients In(Purchases)'!B:B,A3,'Ingredients In(Purchases)'!D:D)) -> 20 | D3: =IF(A3="","",SUMIF('Ingredients Used'!C:C,A3,'Ingredients Used'!E:E)) -> 10 | E3: =IF(A3="","",C3-D3) -> 10 | F3: =IF(A3="","",SUMIF('Ingredients In(Purchases)'!B:B,A3,'Ingredients In(Purchases)'!F:F)) -> 3000 | G3: =IFERROR(F3/C3,"") -> 150
A4: Flavour | B4: Litre | C4: =IF(A4="","",SUMIF('Ingredients In(Purchases)'!B:B,A4,'Ingredients In(Purchases)'!D:D)) -> 20 | D4: =IF(A4="","",SUMIF('Ingredients Used'!C:C,A4,'Ingredients Used'!E:E)) -> 4 | E4: =IF(A4="","",C4-D4) -> 16 | F4: =IF(A4="","",SUMIF('Ingredients In(Purchases)'!B:B,A4,'Ingredients In(Purchases)'!F:F)) -> 3000 | G4: =IFERROR(F4/C4,"") -> 150
A5: Eggs | B5: pcs | C5: =IF(A5="","",SUMIF('Ingredients In(Purchases)'!B:B,A5,'Ingredients In(Purchases)'!D:D)) -> 30 | D5: =IF(A5="","",SUMIF('Ingredients Used'!C:C,A5,'Ingredients Used'!E:E)) -> 35 | E5: =IF(A5="","",C5-D5) -> -5 | F5: =IF(A5="","",SUMIF('Ingredients In(Purchases)'!B:B,A5,'Ingredients In(Purchases)'!F:F)) -> 13500 | G5: =IFERROR(F5/C5,"") -> 450
A6: Fat | B6: kg | C6: =IF(A6="","",SUMIF('Ingredients In(Purchases)'!B:B,A6,'Ingredients In(Purchases)'!D:D)) -> 30 | D6: =IF(A6="","",SUMIF('Ingredients Used'!C:C,A6,'Ingredients Used'!E:E)) -> 25 | E6: =IF(A6="","",C6-D6) -> 5 | F6: =IF(A6="","",SUMIF('Ingredients In(Purchases)'!B:B,A6,'Ingredients In(Purchases)'!F:F)) -> 6000 | G6: =IFERROR(F6/C6,"") -> 200
A7: Sugar | B7: kg | C7: =IF(A7="","",SUMIF('Ingredients In(Purchases)'!B:B,A7,'Ingredients In(Purchases)'!D:D)) -> 50 | D7: =IF(A7="","",SUMIF('Ingredients Used'!C:C,A7,'Ingredients Used'!E:E)) -> 35 | E7: =IF(A7="","",C7-D7) -> 15 | F7: =IF(A7="","",SUMIF('Ingredients In(Purchases)'!B:B,A7,'Ingredients In(Purchases)'!F:F)) -> 7500 | G7: =IFERROR(F7/C7,"") -> 150
A8: Glucose | B8: kg | C8: =IF(A8="","",SUMIF('Ingredients In(Purchases)'!B:B,A8,'Ingredients In(Purchases)'!D:D)) -> 50 | D8: =IF(A8="","",SUMIF('Ingredients Used'!C:C,A8,'Ingredients Used'!E:E)) -> 25 | E8: =IF(A8="","",C8-D8) -> 25 | F8: =IF(A8="","",SUMIF('Ingredients In(Purchases)'!B:B,A8,'Ingredients In(Purchases)'!F:F)) -> 5000 | G8: =IFERROR(F8/C8,"") -> 100
A9: Packaging | B9: pcs | C9: =IF(A9="","",SUMIF('Ingredients In(Purchases)'!B:B,A9,'Ingredients In(Purchases)'!D:D)) -> 60 | D9: =IF(A9="","",SUMIF('Ingredients Used'!C:C,A9,'Ingredients Used'!E:E)) -> 20 | E9: =IF(A9="","",C9-D9) -> 40 | F9: =IF(A9="","",SUMIF('Ingredients In(Purchases)'!B:B,A9,'Ingredients In(Purchases)'!F:F)) -> 9000 | G9: =IFERROR(F9/C9,"") -> 150
C10: =IF(A10="","",SUMIF('Ingredients In(Purchases)'!B:B,A10,'Ingredients In(Purchases)'!D:D)) | D10: =IF(A10="","",SUMIF('Ingredients Used'!C:C,A10,'Ingredients Used'!E:E)) | E10: =IF(A10="","",C10-D10) | F10: =IF(A10="","",SUMIF('Ingredients In(Purchases)'!B:B,A10,'Ingredients In(Purchases)'!F:F)) | G10: =IFERROR(F10/C10,"")
C11: =IF(A11="","",SUMIF('Ingredients In(Purchases)'!B:B,A11,'Ingredients In(Purchases)'!D:D)) | D11: =IF(A11="","",SUMIF('Ingredients Used'!C:C,A11,'Ingredients Used'!E:E)) | E11: =IF(A11="","",C11-D11) | F11: =IF(A11="","",SUMIF('Ingredients In(Purchases)'!B:B,A11,'Ingredients In(Purchases)'!F:F)) | G11: =IFERROR(F11/C11,"")
C12: =IF(A12="","",SUMIF('Ingredients In(Purchases)'!B:B,A12,'Ingredients In(Purchases)'!D:D)) | D12: =IF(A12="","",SUMIF('Ingredients Used'!C:C,A12,'Ingredients Used'!E:E)) | E12: =IF(A12="","",C12-D12) | F12: =IF(A12="","",SUMIF('Ingredients In(Purchases)'!B:B,A12,'Ingredients In(Purchases)'!F:F)) | G12: =IFERROR(F12/C12,"")
C13: =IF(A13="","",SUMIF('Ingredients In(Purchases)'!B:B,A13,'Ingredients In(Purchases)'!D:D)) | D13: =IF(A13="","",SUMIF('Ingredients Used'!C:C,A13,'Ingredients Used'!E:E)) | E13: =IF(A13="","",C13-D13) | F13: =IF(A13="","",SUMIF('Ingredients In(Purchases)'!B:B,A13,'Ingredients In(Purchases)'!F:F)) | G13: =IFERROR(F13/C13,"")
C14: =IF(A14="","",SUMIF('Ingredients In(Purchases)'!B:B,A14,'Ingredients In(Purchases)'!D:D)) | D14: =IF(A14="","",SUMIF('Ingredients Used'!C:C,A14,'Ingredients Used'!E:E)) | E14: =IF(A14="","",C14-D14) | F14: =IF(A14="","",SUMIF('Ingredients In(Purchases)'!B:B,A14,'Ingredients In(Purchases)'!F:F)) | G14: =IFERROR(F14/C14,"")
C15: =IF(A15="","",SUMIF('Ingredients In(Purchases)'!B:B,A15,'Ingredients In(Purchases)'!D:D)) | D15: =IF(A15="","",SUMIF('Ingredients Used'!C:C,A15,'Ingredients Used'!E:E)) | E15: =IF(A15="","",C15-D15) | F15: =IF(A15="","",SUMIF('Ingredients In(Purchases)'!B:B,A15,'Ingredients In(Purchases)'!F:F)) | G15: =IFERROR(F15/C15,"")
C16: =IF(A16="","",SUMIF('Ingredients In(Purchases)'!B:B,A16,'Ingredients In(Purchases)'!D:D)) | D16: =IF(A16="","",SUMIF('Ingredients Used'!C:C,A16,'Ingredients Used'!E:E)) | E16: =IF(A16="","",C16-D16) | F16: =IF(A16="","",SUMIF('Ingredients In(Purchases)'!B:B,A16,'Ingredients In(Purchases)'!F:F)) | G16: =IFERROR(F16/C16,"")
C17: =IF(A17="","",SUMIF('Ingredients In(Purchases)'!B:B,A17,'Ingredients In(Purchases)'!D:D)) | D17: =IF(A17="","",SUMIF('Ingredients Used'!C:C,A17,'Ingredients Used'!E:E)) | E17: =IF(A17="","",C17-D17) | F17: =IF(A17="","",SUMIF('Ingredients In(Purchases)'!B:B,A17,'Ingredients In(Purchases)'!F:F)) | G17: =IFERROR(F17/C17,"")
C18: =IF(A18="","",SUMIF('Ingredients In(Purchases)'!B:B,A18,'Ingredients In(Purchases)'!D:D)) | D18: =IF(A18="","",SUMIF('Ingredients Used'!C:C,A18,'Ingredients Used'!E:E)) | E18: =IF(A18="","",C18-D18) | F18: =IF(A18="","",SUMIF('Ingredients In(Purchases)'!B:B,A18,'Ingredients In(Purchases)'!F:F)) | G18: =IFERROR(F18/C18,"")
C19: =IF(A19="","",SUMIF('Ingredients In(Purchases)'!B:B,A19,'Ingredients In(Purchases)'!D:D)) | D19: =IF(A19="","",SUMIF('Ingredients Used'!C:C,A19,'Ingredients Used'!E:E)) | E19: =IF(A19="","",C19-D19) | F19: =IF(A19="","",SUMIF('Ingredients In(Purchases)'!B:B,A19,'Ingredients In(Purchases)'!F:F)) | G19: =IFERROR(F19/C19,"")
C20: =IF(A20="","",SUMIF('Ingredients In(Purchases)'!B:B,A20,'Ingredients In(Purchases)'!D:D)) | D20: =IF(A20="","",SUMIF('Ingredients Used'!C:C,A20,'Ingredients Used'!E:E)) | E20: =IF(A20="","",C20-D20) | F20: =IF(A20="","",SUMIF('Ingredients In(Purchases)'!B:B,A20,'Ingredients In(Purchases)'!F:F)) | G20: =IFERROR(F20/C20,"")
C21: =IF(A21="","",SUMIF('Ingredients In(Purchases)'!B:B,A21,'Ingredients In(Purchases)'!D:D)) | D21: =IF(A21="","",SUMIF('Ingredients Used'!C:C,A21,'Ingredients Used'!E:E)) | E21: =IF(A21="","",C21-D21) | F21: =IF(A21="","",SUMIF('Ingredients In(Purchases)'!B:B,A21,'Ingredients In(Purchases)'!F:F)) | G21: =IFERROR(F21/C21,"")
... C51: =IF(A51="","",SUMIF('Ingredients In(Purchases)'!B:B,A51,'Ingredients In(Purchases)'!D:D)) | D51: =IF(A51="","",SUMIF('Ingredients Used'!C:C,A51,'Ingredients Used'!E:E)) | E51: =IF(A51="","",C51-D51) | F51: =IF(A51="","",SUMIF('Ingredients In(Purchases)'!B:B,A51,'Ingredients In(Purchases)'!F:F)) | G51: =IFERROR(F51/C51,"")

Sheet Worker Production
A1: Date | B1: Worker | C1: Product | D1: Quantity Produced | E1: Production Hours | F1: KG/Hour | G1: 8KG Units | N1: =IF(OR(L1="",M1=""),"",L1/M1) | O1: =IF(L1="","",L1/8) | P1: =IF(J1="","",8) | Q1: =IF(OR(L1="",P1=0),"",L1/P1) | R1: =IF(L1="","",L1-P1) | S1: =IF(I1="","",TEXT(I1,"mmm-yyyy"))
B2: John | C2: Queen cake | D2: 800 | E2: 2 | F2: =IF(OR(D2="",E2=""),"",D2/E2) -> 400 | G2: =IF(D2="","",D2/8) -> 100 | N2: =IF(OR(L2="",M2=""),"",L2/M2) | O2: =IF(L2="","",L2/8) | P2: =IF(J2="","",8) | Q2: =IF(OR(L2="",P2=0),"",L2/P2) | R2: =IF(L2="","",L2-P2) | S2: =IF(I2="","",TEXT(I2,"mmm-yyyy"))
F3: =IF(OR(D3="",E3=""),"",D3/E3) | G3: =IF(D3="","",D3/8) | N3: =IF(OR(L3="",M3=""),"",L3/M3) | O3: =IF(L3="","",L3/8) | P3: =IF(J3="","",8) | Q3: =IF(OR(L3="",P3=0),"",L3/P3) | R3: =IF(L3="","",L3-P3) | S3: =IF(I3="","",TEXT(I3,"mmm-yyyy"))
F4: =IF(OR(D4="",E4=""),"",D4/E4) | G4: =IF(D4="","",D4/8) | N4: =IF(OR(L4="",M4=""),"",L4/M4) | O4: =IF(L4="","",L4/8) | P4: =IF(J4="","",8) | Q4: =IF(OR(L4="",P4=0),"",L4/P4) | R4: =IF(L4="","",L4-P4) | S4: =IF(I4="","",TEXT(I4,"mmm-yyyy"))
F5: =IF(OR(D5="",E5=""),"",D5/E5) | G5: =IF(D5="","",D5/8) | N5: =IF(OR(L5="",M5=""),"",L5/M5) | O5: =IF(L5="","",L5/8) | P5: =IF(J5="","",8) | Q5: =IF(OR(L5="",P5=0),"",L5/P5) | R5: =IF(L5="","",L5-P5) | S5: =IF(I5="","",TEXT(I5,"mmm-yyyy"))
F6: =IF(OR(D6="",E6=""),"",D6/E6) | G6: =IF(D6="","",D6/8) | N6: =IF(OR(L6="",M6=""),"",L6/M6) | O6: =IF(L6="","",L6/8) | P6: =IF(J6="","",8) | Q6: =IF(OR(L6="",P6=0),"",L6/P6) | R6: =IF(L6="","",L6-P6) | S6: =IF(I6="","",TEXT(I6,"mmm-yyyy"))
F7: =IF(OR(D7="",E7=""),"",D7/E7) | G7: =IF(D7="","",D7/8) | N7: =IF(OR(L7="",M7=""),"",L7/M7) | O7: =IF(L7="","",L7/8) | P7: =IF(J7="","",8) | Q7: =IF(OR(L7="",P7=0),"",L7/P7) | R7: =IF(L7="","",L7-P7) | S7: =IF(I7="","",TEXT(I7,"mmm-yyyy"))
F8: =IF(OR(D8="",E8=""),"",D8/E8) | G8: =IF(D8="","",D8/8) | N8: =IF(OR(L8="",M8=""),"",L8/M8) | O8: =IF(L8="","",L8/8) | P8: =IF(J8="","",8) | Q8: =IF(OR(L8="",P8=0),"",L8/P8) | R8: =IF(L8="","",L8-P8) | S8: =IF(I8="","",TEXT(I8,"mmm-yyyy"))
F9: =IF(OR(D9="",E9=""),"",D9/E9) | G9: =IF(D9="","",D9/8) | N9: =IF(OR(L9="",M9=""),"",L9/M9) | O9: =IF(L9="","",L9/8) | P9: =IF(J9="","",8) | Q9: =IF(OR(L9="",P9=0),"",L9/P9) | R9: =IF(L9="","",L9-P9) | S9: =IF(I9="","",TEXT(I9,"mmm-yyyy"))
F10: =IF(OR(D10="",E10=""),"",D10/E10) | G10: =IF(D10="","",D10/8) | N10: =IF(OR(L10="",M10=""),"",L10/M10) | O10: =IF(L10="","",L10/8) | P10: =IF(J10="","",8) | Q10: =IF(OR(L10="",P10=0),"",L10/P10) | R10: =IF(L10="","",L10-P10) | S10: =IF(I10="","",TEXT(I10,"mmm-yyyy"))
F11: =IF(OR(D11="",E11=""),"",D11/E11) | G11: =IF(D11="","",D11/8) | N11: =IF(OR(L11="",M11=""),"",L11/M11) | O11: =IF(L11="","",L11/8) | P11: =IF(J11="","",8) | Q11: =IF(OR(L11="",P11=0),"",L11/P11) | R11: =IF(L11="","",L11-P11) | S11: =IF(I11="","",TEXT(I11,"mmm-yyyy"))
F12: =IF(OR(D12="",E12=""),"",D12/E12) | G12: =IF(D12="","",D12/8) | N12: =IF(OR(L12="",M12=""),"",L12/M12) | O12: =IF(L12="","",L12/8) | P12: =IF(J12="","",8) | Q12: =IF(OR(L12="",P12=0),"",L12/P12) | R12: =IF(L12="","",L12-P12) | S12: =IF(I12="","",TEXT(I12,"mmm-yyyy"))
F13: =IF(OR(D13="",E13=""),"",D13/E13) | G13: =IF(D13="","",D13/8) | N13: =IF(OR(L13="",M13=""),"",L13/M13) | O13: =IF(L13="","",L13/8) | P13: =IF(J13="","",8) | Q13: =IF(OR(L13="",P13=0),"",L13/P13) | R13: =IF(L13="","",L13-P13) | S13: =IF(I13="","",TEXT(I13,"mmm-yyyy"))
F14: =IF(OR(D14="",E14=""),"",D14/E14) | G14: =IF(D14="","",D14/8) | N14: =IF(OR(L14="",M14=""),"",L14/M14) | O14: =IF(L14="","",L14/8) | P14: =IF(J14="","",8) | Q14: =IF(OR(L14="",P14=0),"",L14/P14) | R14: =IF(L14="","",L14-P14) | S14: =IF(I14="","",TEXT(I14,"mmm-yyyy"))
... F100: =IF(OR(D100="",E100=""),"",D100/E100) | G100: =IF(D100="","",D100/8) | N100: =IF(OR(L100="",M100=""),"",L100/M100) | O100: =IF(L100="","",L100/8) | P100: =IF(J100="","",8) | Q100: =IF(OR(L100="",P100=0),"",L100/P100) | R100: =IF(L100="","",L100-P100) | S100: =IF(I100="","",TEXT(I100,"mmm-yyyy"))
F101: =IF(OR(D101="",E101=""),"",D101/E101) | G101: =IF(D101="","",D101/8)

Sheet Sales Returns
A1: Date | B1: Customer | C1: Invoice No. | D1: Product | E1: Quantity Returned | F1: Unit Cost | G1: Return Value | H1: Reason
G2: =IF(OR(E2="",F2=""),"",E2*F2)
G3: =IF(OR(E3="",F3=""),"",E3*F3)
G4: =IF(OR(E4="",F4=""),"",E4*F4)
G5: =IF(OR(E5="",F5=""),"",E5*F5)
G6: =IF(OR(E6="",F6=""),"",E6*F6)
G7: =IF(OR(E7="",F7=""),"",E7*F7)
G8: =IF(OR(E8="",F8=""),"",E8*F8)
G9: =IF(OR(E9="",F9=""),"",E9*F9)
G10: =IF(OR(E10="",F10=""),"",E10*F10)
G11: =IF(OR(E11="",F11=""),"",E11*F11)
G12: =IF(OR(E12="",F12=""),"",E12*F12)
G13: =IF(OR(E13="",F13=""),"",E13*F13)
... G201: =IF(OR(E201="",F201=""),"",E201*F201)

Sheet Sales Damages
A1: Date | B1: Product | C1: Quantity Damaged | D1: Unit Cost | E1: Damage Value | F1: Reason | G1: Department/Worker | H1: Approved By
E2: =IF(OR(C2="",D2=""),"",C2*D2)
E3: =IF(OR(C3="",D3=""),"",C3*D3)
E4: =IF(OR(C4="",D4=""),"",C4*D4)
E5: =IF(OR(C5="",D5=""),"",C5*D5)
E6: =IF(OR(C6="",D6=""),"",C6*D6)
E7: =IF(OR(C7="",D7=""),"",C7*D7)
E8: =IF(OR(C8="",D8=""),"",C8*D8)
E9: =IF(OR(C9="",D9=""),"",C9*D9)
E10: =IF(OR(C10="",D10=""),"",C10*D10)
E11: =IF(OR(C11="",D11=""),"",C11*D11)
E12: =IF(OR(C12="",D12=""),"",C12*D12)
E13: =IF(OR(C13="",D13=""),"",C13*D13)
... E201: =IF(OR(C201="",D201=""),"",C201*D201)

Sheet Customer Management
A1: Customer ID | B1: Customer Name | C1: Phone | D1: Location | E1: Opening Balance | F1: Credit Limit | G1: Total Sales | H1: Payments | I1: Outstanding Balance | J1: Last Transaction Date | K1: Status
I2: =IF(A2="","",E2+G2-H2) | K2: =IF(A2="","",IF(I2>F2,"OVER LIMIT",IF(I2>0,"ACTIVE CREDIT","CLEAR")))
I3: =IF(A3="","",E3+G3-H3) | K3: =IF(A3="","",IF(I3>F3,"OVER LIMIT",IF(I3>0,"ACTIVE CREDIT","CLEAR")))
I4: =IF(A4="","",E4+G4-H4) | K4: =IF(A4="","",IF(I4>F4,"OVER LIMIT",IF(I4>0,"ACTIVE CREDIT","CLEAR")))
I5: =IF(A5="","",E5+G5-H5) | K5: =IF(A5="","",IF(I5>F5,"OVER LIMIT",IF(I5>0,"ACTIVE CREDIT","CLEAR")))
I6: =IF(A6="","",E6+G6-H6) | K6: =IF(A6="","",IF(I6>F6,"OVER LIMIT",IF(I6>0,"ACTIVE CREDIT","CLEAR")))
I7: =IF(A7="","",E7+G7-H7) | K7: =IF(A7="","",IF(I7>F7,"OVER LIMIT",IF(I7>0,"ACTIVE CREDIT","CLEAR")))
I8: =IF(A8="","",E8+G8-H8) | K8: =IF(A8="","",IF(I8>F8,"OVER LIMIT",IF(I8>0,"ACTIVE CREDIT","CLEAR")))
I9: =IF(A9="","",E9+G9-H9) | K9: =IF(A9="","",IF(I9>F9,"OVER LIMIT",IF(I9>0,"ACTIVE CREDIT","CLEAR")))
I10: =IF(A10="","",E10+G10-H10) | K10: =IF(A10="","",IF(I10>F10,"OVER LIMIT",IF(I10>0,"ACTIVE CREDIT","CLEAR")))
I11: =IF(A11="","",E11+G11-H11) | K11: =IF(A11="","",IF(I11>F11,"OVER LIMIT",IF(I11>0,"ACTIVE CREDIT","CLEAR")))
I12: =IF(A12="","",E12+G12-H12) | K12: =IF(A12="","",IF(I12>F12,"OVER LIMIT",IF(I12>0,"ACTIVE CREDIT","CLEAR")))
I13: =IF(A13="","",E13+G13-H13) | K13: =IF(A13="","",IF(I13>F13,"OVER LIMIT",IF(I13>0,"ACTIVE CREDIT","CLEAR")))
... I201: =IF(A201="","",E201+G201-H201) | K201: =IF(A201="","",IF(I201>F201,"OVER LIMIT",IF(I201>0,"ACTIVE CREDIT","CLEAR")))

Sheet Daily Profit
A1: Date | B1: Gross Sales | C1: Sales Returns | D1: Net Sales | E1: COGS/Production Cost | F1: Sales Damages | G1: Other Expenses | H1: Gross Profit | I1: Net Profit | J1: Profit Margin %
D2: =IF(A2="","",B2-C2) | H2: =IF(A2="","",D2-E2) | I2: =IF(A2="","",H2-F2-G2) | J2: =IFERROR(I2/D2,"")
D3: =IF(A3="","",B3-C3) | H3: =IF(A3="","",D3-E3) | I3: =IF(A3="","",H3-F3-G3) | J3: =IFERROR(I3/D3,"")
D4: =IF(A4="","",B4-C4) | H4: =IF(A4="","",D4-E4) | I4: =IF(A4="","",H4-F4-G4) | J4: =IFERROR(I4/D4,"")
D5: =IF(A5="","",B5-C5) | H5: =IF(A5="","",D5-E5) | I5: =IF(A5="","",H5-F5-G5) | J5: =IFERROR(I5/D5,"")
D6: =IF(A6="","",B6-C6) | H6: =IF(A6="","",D6-E6) | I6: =IF(A6="","",H6-F6-G6) | J6: =IFERROR(I6/D6,"")
D7: =IF(A7="","",B7-C7) | H7: =IF(A7="","",D7-E7) | I7: =IF(A7="","",H7-F7-G7) | J7: =IFERROR(I7/D7,"")
D8: =IF(A8="","",B8-C8) | H8: =IF(A8="","",D8-E8) | I8: =IF(A8="","",H8-F8-G8) | J8: =IFERROR(I8/D8,"")
D9: =IF(A9="","",B9-C9) | H9: =IF(A9="","",D9-E9) | I9: =IF(A9="","",H9-F9-G9) | J9: =IFERROR(I9/D9,"")
D10: =IF(A10="","",B10-C10) | H10: =IF(A10="","",D10-E10) | I10: =IF(A10="","",H10-F10-G10) | J10: =IFERROR(I10/D10,"")
D11: =IF(A11="","",B11-C11) | H11: =IF(A11="","",D11-E11) | I11: =IF(A11="","",H11-F11-G11) | J11: =IFERROR(I11/D11,"")
D12: =IF(A12="","",B12-C12) | H12: =IF(A12="","",D12-E12) | I12: =IF(A12="","",H12-F12-G12) | J12: =IFERROR(I12/D12,"")
D13: =IF(A13="","",B13-C13) | H13: =IF(A13="","",D13-E13) | I13: =IF(A13="","",H13-F13-G13) | J13: =IFERROR(I13/D13,"")
... D366: =IF(A366="","",B366-C366) | H366: =IF(A366="","",D366-E366) | I366: =IF(A366="","",H366-F366-G366) | J366: =IFERROR(I366/D366,"")

Sheet Inventory Summary
A1: Product | B1: Opening Inventory | C1: Production Added | D1: Sales Deducted | E1: Sales Returns Added | F1: Damages Deducted | G1: Closing Inventory
G2: =IF(A2="","",B2+C2+E2-D2-F2)
G3: =IF(A3="","",B3+C3+E3-D3-F3)
G4: =IF(A4="","",B4+C4+E4-D4-F4)
G5: =IF(A5="","",B5+C5+E5-D5-F5)
G6: =IF(A6="","",B6+C6+E6-D6-F6)
G7: =IF(A7="","",B7+C7+E7-D7-F7)
G8: =IF(A8="","",B8+C8+E8-D8-F8)
G9: =IF(A9="","",B9+C9+E9-D9-F9)
G10: =IF(A10="","",B10+C10+E10-D10-F10)
G11: =IF(A11="","",B11+C11+E11-D11-F11)
G12: =IF(A12="","",B12+C12+E12-D12-F12)
G13: =IF(A13="","",B13+C13+E13-D13-F13)
... G201: =IF(A201="","",B201+C201+E201-D201-F201)
